[{"name":"Виктор","surname":"Валентинович","lastName":"Степанов","contacts":[{"type":"+79518397652","value":"Телефон"}],"id":"1677429742929","updatedAt":"2023-02-26T16:42:22.929Z","createdAt":"2023-02-26T16:42:22.929Z"},{"name":"Виктор","surname":"Семенович","lastName":"Филатов","contacts":[],"id":"1677865809758","updatedAt":"2023-03-03T17:50:09.758Z","createdAt":"2023-03-03T17:50:09.758Z"},{"name":"Ааааа","surname":"Ааааа","lastName":"ААаааа","contacts":[],"id":"1677865953381","updatedAt":"2023-03-03T17:52:33.381Z","createdAt":"2023-03-03T17:52:33.381Z"}]